codemate_ai/__init__.py
codemate_ai/core.py
codemate_ai/magics.py
codemate_ai/providers.py
codemate_ai-0.1.4.dist-info/LICENSE
codemate_ai-0.1.4.dist-info/METADATA
codemate_ai-0.1.4.dist-info/WHEEL
codemate_ai-0.1.4.dist-info/entry_points.txt
codemate_ai-0.1.4.dist-info/top_level.txt
codemate_ai-0.1.4.dist-info/RECORD
