Metadata-Version: 2.2
Name: codemate_ai
Version: 0.1.4
Summary: CodeMate
Home-page: https://github.com/yourusername/codemate-ai
Author: Manan Gupta
Author-email: manangupta9901@gmail.com
Classifier: Programming Language :: Python :: 3
Classifier: License :: OSI Approved :: MIT License
Classifier: Operating System :: OS Independent
Requires-Python: >=3.6
License-File: LICENSE
Requires-Dist: torch
Requires-Dist: transformers
Requires-Dist: huggingface_hub
Requires-Dist: google-generativeai
Requires-Dist: requests
Requires-Dist: IPython
Requires-Dist: nbformat
Requires-Dist: pytest
Requires-Dist: pytorch-lightning
Requires-Dist: jupyter_server
Requires-Dist: astor
Requires-Dist: pygments
Dynamic: author
Dynamic: author-email
Dynamic: classifier
Dynamic: description
Dynamic: description-content-type
Dynamic: home-page
Dynamic: requires-dist
Dynamic: requires-python
Dynamic: summary
